symbolic_qiskit/__init__.py
symbolic_qiskit/circuit/__init__.py
symbolic_qiskit/circuit/base.py
symbolic_qiskit/circuit/build.py
symbolic_qiskit/circuit/circuit_backend.py
symbolic_qiskit/circuit/circuit_inspector.py
symbolic_qiskit/circuit/measurement_circuit.py
symbolic_qiskit/circuit/unitary_circuit.py
symbolic_qiskit/circuit/utils.py
symbolic_qiskit/gate/__init__.py
symbolic_qiskit/gate/base.py
symbolic_qiskit/gate/utils.py
symbolic_qiskit/gate/standard_gates/__init__.py
symbolic_qiskit/gate/standard_gates/dcx.py
symbolic_qiskit/gate/standard_gates/ecr.py
symbolic_qiskit/gate/standard_gates/h.py
symbolic_qiskit/gate/standard_gates/i.py
symbolic_qiskit/gate/standard_gates/iswap.py
symbolic_qiskit/gate/standard_gates/p.py
symbolic_qiskit/gate/standard_gates/r.py
symbolic_qiskit/gate/standard_gates/rx.py
symbolic_qiskit/gate/standard_gates/rxx.py
symbolic_qiskit/gate/standard_gates/ry.py
symbolic_qiskit/gate/standard_gates/ryy.py
symbolic_qiskit/gate/standard_gates/rz.py
symbolic_qiskit/gate/standard_gates/rzx.py
symbolic_qiskit/gate/standard_gates/rzz.py
symbolic_qiskit/gate/standard_gates/s.py
symbolic_qiskit/gate/standard_gates/swap.py
symbolic_qiskit/gate/standard_gates/sx.py
symbolic_qiskit/gate/standard_gates/t.py
symbolic_qiskit/gate/standard_gates/u.py
symbolic_qiskit/gate/standard_gates/u1.py
symbolic_qiskit/gate/standard_gates/u2.py
symbolic_qiskit/gate/standard_gates/u3.py
symbolic_qiskit/gate/standard_gates/x.py
symbolic_qiskit/gate/standard_gates/xx_minus_yy.py
symbolic_qiskit/gate/standard_gates/xx_plus_yy.py
symbolic_qiskit/gate/standard_gates/y.py
symbolic_qiskit/gate/standard_gates/z.py
symbolic_qiskit/layer/__init__.py
symbolic_qiskit/layer/base.py
symbolic_qiskit/layer/build.py
symbolic_qiskit/layer/measurement_layer.py
symbolic_qiskit/layer/standard_layer.py
symbolic_qiskit/layer/utils.py
symbolic_qiskit-0.1.0a1.dist-info/licenses/LICENSE
symbolic_qiskit-0.1.0a1.dist-info/METADATA
symbolic_qiskit-0.1.0a1.dist-info/WHEEL
symbolic_qiskit-0.1.0a1.dist-info/top_level.txt
symbolic_qiskit-0.1.0a1.dist-info/RECORD
